{"otherData": {},"traceEvents":[{"cat":"function","dur":4,"name":"GLVertexBuffer","ph":"X","pid":0,"tid":2498957170,"ts":1689694823699996},{"cat":"function","dur":0,"name":"SetData","ph":"X","pid":0,"tid":2498957170,"ts":1689694823700037},{"cat":"function","dur":19,"name":"GLIndexBuffer","ph":"X","pid":0,"tid":2498957170,"ts":1689694823700047},{"cat":"function","dur":3,"name":"GLVertexArray","ph":"X","pid":0,"tid":2498957170,"ts":1689694823700077},{"cat":"function","dur":0,"name":"SetIndexBuffer","ph":"X","pid":0,"tid":2498957170,"ts":1689694823700086},{"cat":"function","dur":5,"name":"AddVertexBuffer","ph":"X","pid":0,"tid":2498957170,"ts":1689694823700091},{"cat":"function","dur":0,"name":"Bind","ph":"X","pid":0,"tid":2498957170,"ts":1689694823700100}]}